extratools_core/__init__.py
extratools_core/cli.py
extratools_core/clitools.py
extratools_core/config.py
extratools_core/crudl.py
extratools_core/debug.py
extratools_core/debugtools.py
extratools_core/dict.py
extratools_core/dicttools.py
extratools_core/func.py
extratools_core/functools.py
extratools_core/iter.py
extratools_core/itertools.py
extratools_core/json.py
extratools_core/jsontools.py
extratools_core/logging.py
extratools_core/math.py
extratools_core/mathtools.py
extratools_core/path.py
extratools_core/pathtools.py
extratools_core/print.py
extratools_core/printtools.py
extratools_core/py.typed
extratools_core/str.py
extratools_core/strtools.py
extratools_core/table.py
extratools_core/tabletools.py
extratools_core/test.py
extratools_core/testtools.py
extratools_core/trie.py
extratools_core/typing.py
extratools_core/seq/__init__.py
extratools_core/seq/common.py
extratools_core/seq/subseq.py
extratools_core/set/__init__.py
extratools_core/set/subset.py
extratools_core-0.1.34.dist-info/METADATA
extratools_core-0.1.34.dist-info/WHEEL
extratools_core-0.1.34.dist-info/licenses/LICENSE
extratools_core-0.1.34.dist-info/RECORD
