Metadata-Version: 2.4
Name: extratools-core
Version: 0.1.34
Project-URL: Repository, https://github.com/chuanconggao/extratools-core
Author-email: Chuancong Gao <chuanconggao@users.noreply.github.com>
License-Expression: MIT
License-File: LICENSE
Requires-Python: >=3.12
Requires-Dist: cachetools>=6.1.0
Requires-Dist: pyyaml>=6.0.2
Requires-Dist: simple-zstd>=0.1.1
Requires-Dist: sortedcontainers>=2.4.0
Requires-Dist: toolz>=1.0.0
Provides-Extra: cli
Requires-Dist: wcwidth>=0.2.13; extra == 'cli'
